MANIFEST.in
README.md
setup.py
bearychat/__init__.py
bearychat/incoming.py
bearychat_py.egg-info/PKG-INFO
bearychat_py.egg-info/SOURCES.txt
bearychat_py.egg-info/dependency_links.txt
bearychat_py.egg-info/not-zip-safe
bearychat_py.egg-info/pbr.json
bearychat_py.egg-info/requires.txt
bearychat_py.egg-info/top_level.txt
tests/test_incoming.py