Metadata-Version: 1.1
Name: bearychat-py
Version: 0.3.1
Summary: A simple package for interacting with bearychat.
Home-page: https://github.com/bcho/bearychat-py
Author: hbc
Author-email: bcxxxxxx@gmail.com
License: MIT
Platform: UNKNOWN
Classifier: Intended Audience :: Developers
Classifier: Intended Audience :: System Administrators
Classifier: Operating System :: OS Independent
Classifier: Topic :: Software Development
